README.md
setup.py
pypework/__init__.py
pypework.egg-info/PKG-INFO
pypework.egg-info/SOURCES.txt
pypework.egg-info/dependency_links.txt
pypework.egg-info/not-zip-safe
pypework.egg-info/top_level.txt