Metadata-Version: 1.0
Name: pypework
Version: 0.8
Summary: Functional pipeline library for Python
Home-page: http://github.com/andybrice/pypework
Author: Andy Brice
Author-email: andybrice@users.noreply.github.com
License: MIT
Platform: UNKNOWN
